lukhed_markets/__init__.py
lukhed_markets/examples.py
lukhed_markets/fred.py
lukhed_markets/kalshi.py
lukhed_markets/polymarket.py
lukhed_markets/polymarket_tags.py
lukhed_markets/predictit.py
lukhed_markets-0.3.0.dist-info/LICENSE
lukhed_markets-0.3.0.dist-info/METADATA
lukhed_markets-0.3.0.dist-info/WHEEL
lukhed_markets-0.3.0.dist-info/top_level.txt
lukhed_markets-0.3.0.dist-info/RECORD
