Metadata-Version: 2.1
Name: lukhed-markets
Version: 0.3.0
Summary: A collection of broad market analysis functions and api wrappers
Home-page: https://github.com/lukhed/lukhed_markets
Author: lukhed
Author-email: lukhed.mail@gmail.com
Classifier: Programming Language :: Python :: 3
Classifier: License :: OSI Approved :: MIT License
Classifier: Operating System :: OS Independent
Requires-Python: >=3.10
License-File: LICENSE
Requires-Dist: lukhed-basic-utils>=1.6.9
Requires-Dist: fredapi>=0.5.2
Requires-Dist: py-clob-client>=0.34.1
Requires-Dist: websocket-client>=1.9.0
Requires-Dist: web3>=7.14.0
